juungle/__init__.py
juungle/auth.py
juungle/exception.py
juungle/nft.py
juungle/rate_limiter.py
juungle/tokens.py
juungle/user.py
juungle-0.6.2.dist-info/LICENSE
juungle-0.6.2.dist-info/METADATA
juungle-0.6.2.dist-info/WHEEL
juungle-0.6.2.dist-info/top_level.txt
juungle-0.6.2.dist-info/RECORD
