Metadata-Version: 2.1
Name: juungle
Version: 0.6.2
Summary: Juungle python package for juungle.net
Home-page: https://github.com/Juungle/juungle-python
Author: Eduardo Elias
Author-email: camponez@gmail.com
License: MIT
Project-URL: Bug Tracker, https://github.com/Juungle/juungle-python/issues
Project-URL: Source Code, https://github.com/Juungle/juungle-python
Keywords: juungle.net api nfts
Platform: UNKNOWN
Classifier: Development Status :: 3 - Alpha
Classifier: Programming Language :: Python :: 3
Classifier: License :: OSI Approved :: MIT License
Classifier: Operating System :: OS Independent
Classifier: Topic :: Utilities
Requires-Python: >=3.6
Requires-Dist: requests
Provides-Extra: test
Requires-Dist: pytest (>=2.7.3) ; extra == 'test'
